torch_admp/__init__.py
torch_admp/_version.py
torch_admp/base_force.py
torch_admp/electrode.py
torch_admp/env.py
torch_admp/nblist.py
torch_admp/optimizer.py
torch_admp/pme.py
torch_admp/qeq.py
torch_admp/recip.py
torch_admp/spatial.py
torch_admp/utils.py
torch_admp-1.1.5.dist-info/licenses/LICENSE
torch_admp-1.1.5.dist-info/METADATA
torch_admp-1.1.5.dist-info/WHEEL
torch_admp-1.1.5.dist-info/top_level.txt
torch_admp-1.1.5.dist-info/RECORD
