Metadata-Version: 2.4
Name: torch_admp
Version: 1.1.5
Summary: ADMP in PyTorch backend
License: SPDX-License-Identifier: LGPL-3.0-or-later
Project-URL: Homepage, https://github.com/ChiahsinChu/torch-admp
Requires-Python: >=3.10
License-File: LICENSE
Requires-Dist: torch<2.10,>=2.1.0
Requires-Dist: torchopt==0.7.3
Requires-Dist: numpy>=1.21
Requires-Dist: scipy>=1.6.0
Requires-Dist: ase
Requires-Dist: ml_dtypes
Provides-Extra: vesin
Requires-Dist: vesin[torch]; extra == "vesin"
Provides-Extra: test
Requires-Dist: pytest; extra == "test"
Requires-Dist: pytest-cov; extra == "test"
Requires-Dist: pytest-html; extra == "test"
Requires-Dist: mypy; extra == "test"
Requires-Dist: openmm>=7.7.0; extra == "test"
Requires-Dist: jax<=0.4.20,>=0.4.1; extra == "test"
Requires-Dist: jaxlib<=0.4.20,>=0.4.1; extra == "test"
Requires-Dist: numpy<2.0,>=1.21; extra == "test"
Requires-Dist: freud-analysis==3.4.0; extra == "test"
Provides-Extra: docs
Requires-Dist: mkdocs>=1.5.0; extra == "docs"
Requires-Dist: mkdocs-material>=9.0.0; extra == "docs"
Requires-Dist: mkdocstrings[python]>=0.20.0; extra == "docs"
Requires-Dist: mkdocs-glightbox>=0.3.0; extra == "docs"
Requires-Dist: pymdown-extensions>=10.0.0; extra == "docs"
Requires-Dist: mkdocs-git-revision-date-localized-plugin>=1.2.0; extra == "docs"
Requires-Dist: mkdocs-awesome-pages-plugin>=2.8.0; extra == "docs"
Requires-Dist: mkdocs-gen-files>=0.5.0; extra == "docs"
Requires-Dist: griffe>=0.48.0; extra == "docs"
Dynamic: license-file
